<?xml version="1.0" encoding="UTF-8"?>
<xml>
 <Geometry type="TensorBSpline2">
  <Basis type="TensorBSplineBasis2">
   <Basis type="BSplineBasis" index="0">
    <KnotVector degree="3">0 0 0 0 1 2 3 4 5 5 5 5</KnotVector>
   </Basis>
   <Basis type="BSplineBasis" index="1">
    <KnotVector degree="3">0 0 0 0 1 2 3 4 5 6 6 6 6</KnotVector>
   </Basis>
  </Basis>
  <coefs geoDim="3"> 8 -50 0 8 -47 0 8 -45 0 8 -42 0 8 -40 0 8 -37 0 8 -34 0 8 -33 0 11 -50 0 11 -47 0 11 -45 0 11 -42 0 11 -40 0 11 -37 0 11 -34 0 11 -33 0 14 -50 0 14.072 -47.36 4.351999999999999 13.664 -45.088 7.031999999999999 13.21988450164333 -42.248 7.874288745891671 13.21188450164333 -39.68 7.298288745891671 13.664 -36.696 4.672 14 -34 0 14 -33 0 18 -50 0 17.584 -47.456 6.528 16.98765350492999 -44.912 10.01486623767502 16.24730700985999 -42.472 10.94973247535003 16.25530700985999 -39.44 10.08573247535003 17.01965350492999 -36.776 6.558866237675015 18 -34 0 18 -33 0 21 -50 0 20.97965350493 -47.32 6.750866237675015 20.33896051478998 -44.904 10.07659871302504 19.56592102957996 -42.24 10.38519742605009 19.55792102957996 -39.672 9.52119742605009 20.33096051478998 -36.776 6.356598713025045 21 -34 0 21 -33 0 25 -50 0 24.55153800657332 -47.312 6.145154983566686 23.89026752464997 -44.768 8.866331188375074 23.17711254108328 -42.28 9.033218647291791 23.18511254108328 -39.632 8.169218647291792 23.96638302300664 -36.92 5.464042442483404 25 -34 0 25 -33 0 28 -50 0 28.13165350492999 -47.264 3.966866237675014 27.84296051478998 -44.8 5.876598713025045 27.42603652793663 -42.2 5.950908680158419 27.41803652793663 -39.728 5.374908680158418 27.79496051478998 -36.936 3.572598713025045 28 -34 0 28 -33 0 32 -50 0 32 -47 0 32 -45 0 32 -42 0 32 -40 0 32 -37 0 32 -34 0 32 -33 0 35 -50 0 35 -47 0 35 -45 0 35 -42 0 35 -40 0 35 -37 0 35 -34 0 35 -33 0</coefs>
 </Geometry>
 <Geometry type="TensorBSpline2">
  <Basis type="TensorBSplineBasis2">
   <Basis type="BSplineBasis" index="0">
    <KnotVector degree="3">0 0 0 0 1 2 3 4 5 5 5 5</KnotVector>
   </Basis>
   <Basis type="BSplineBasis" index="1">
    <KnotVector degree="3">0 0 0 0 1 2 3 4 5 6 6 6 6</KnotVector>
   </Basis>
  </Basis>
  <coefs geoDim="3"> -26 -50 0 -26 -47 0 -26 -45 0 -26 -42 0 -26 -40 0 -26 -37 0 -26 -34 0 -26 -33 0 -23 -50 0 -23 -47 0 -23 -45 0 -23 -42 0 -23 -40 0 -23 -37 0 -23 -34 0 -23 -33 0 -20 -50 0 -20 -47 12 -20 -45 12 -26 -48 19 -26 -34 19 -20 -37 12 -20 -34 0 -20 -33 0 -16 -50 0 -16 -47 12 -16 -45 12 -16 -42 12 -16 -40 12 -16 -37 12 -16 -34 0 -16 -33 0 -13 -50 0 -13 -47 12 -13 -45 12 -16 -42 9 -16 -40 9 -13 -37 12 -13 -34 0 -13 -33 0 -9 -50 0 -9 -47 12 -9 -45 12 -14.51443729458359 -42 5.286093236458962 -14.51443729458359 -40 5.286093236458962 -9 -37 12 -9 -34 0 -9 -33 0 -6 -50 0 -6 -47 12 -6 -45 12 -6 -42 12 -6 -40 12 -6 -37 12 -6 -34 0 -6 -33 0 -2 -50 0 -2 -47 0 -2 -45 0 -2 -42 0 -2 -40 0 -2 -37 0 -2 -34 0 -2 -33 0 1 -50 0 1 -47 0 1 -45 0 1 -42 0 1 -40 0 1 -37 0 1 -34 0 1 -33 0</coefs>
 </Geometry>
 <Geometry type="TensorBSpline2">
  <Basis type="TensorBSplineBasis2">
   <Basis type="BSplineBasis" index="0">
    <KnotVector degree="3">0 0 0 0 4.570609835176398 9.14506643581444 10.46788633955679 11.79109896711383 12.7555146347201 13.7206266801095 14.63194564671659 15.54813305244663 16.12521737949137 16.70481263559845 17.50476270818472 18.29512533029413 19.18363558575445 20.09961664790639 20.56315312673546 21.02366494080325 21.94846532611753 22.87152729068178 25.15958133910473 27.44759124303697 32.02021068748245 36.59282940448932 36.59282940448932 36.59282940448932 36.59282940448932</KnotVector>
   </Basis>
   <Basis type="BSplineBasis" index="1">
    <KnotVector degree="3">-3 -2 -1 0 1 2 3 4 5 6 7 8 9</KnotVector>
   </Basis>
  </Basis>
  <coefs geoDim="3"> 4.348928233542598 -21.10754271902344 3.13324218826829 5.783323645741007 -20.81561297672496 3.133242188268288 8.620551790257359 -20.19301446342274 3.13324218826829 12.05464630530952 -22.22276951190605 2.330029551600019 14.39156247147932 -22.39517433720579 2.163975056302921 15.83354835144833 -22.10154845012024 2.130118060962435 16.85313851838361 -21.70427869024211 2.123342581395765 17.62539715587625 -21.3096912106959 2.122175532793416 18.23382161025673 -20.92633496926805 2.121979324485286 18.66933062627186 -20.57073219600362 2.121979324485287 18.93984749014791 -20.23256675449064 2.121979324485286 19.07764013186653 -19.86894836611156 2.121979324485287 19.10098586093496 -19.43029231143374 2.121979324485287 19.07326642422995 -18.93438837705636 2.121979324485286 19.02386063935434 -18.45067871684275 2.121979324485287 18.87155225778202 -18.08868300324772 2.121979324485288 18.58749765363009 -17.87654013060773 2.122175532793416 18.12900246248176 -17.68970347916105 2.123342581395765 17.34817189531539 -17.46360243639077 2.130118060962434 16.00516710381799 -17.24693326358207 2.163975056302923 13.91370393379888 -17.48767197183128 2.330029551600021 10.60883632518916 -19.45513850232674 3.133242188268292 6.974237372973668 -18.23538196237149 3.133242188268287 4.089492658331778 -17.25723777183232 3.13324218826829 2.635229947091702 -16.76219476360893 3.13324218826829 5.45240161208984 -26.53295349688072 6.365850645371812 6.943746183290763 -26.22953042038311 6.365850645371806 9.919018350744217 -25.57660162892268 6.365850645371812 13.29004224164584 -24.65916787915436 6.365850645371809 15.56982909001747 -23.87080155638711 6.365850645371809 16.68498303905838 -23.42806091713169 6.365850645371812 17.67238326684275 -22.97235828017932 6.365850645371815 18.50525389660083 -22.51984447906943 6.365850645371811 19.27864612319744 -21.99962144566948 6.365850645371809 19.8754399338148 -21.45540466566841 6.365850645371814 20.27806393299279 -20.88797221159571 6.365850645371809 20.52728527264048 -20.27399150856752 6.365850645371812 20.55498513309119 -19.54076576740544 6.365850645371812 20.48153489527025 -18.72073493645393 6.365850645371808 20.39602340552332 -17.84834871989033 6.365850645371813 20.06100917982081 -17.14452883764008 6.365850645371815 19.56269144676174 -16.77258343065338 6.365850645371811 19.01543366009083 -16.47791882684101 6.365850645371813 18.29322613011837 -16.20180848418653 6.365850645371808 16.99966265015561 -15.74986412222862 6.365850645371813 15.24947111906908 -15.16646727012917 6.365850645371814 12.36380726227661 -14.20404962071607 6.365850645371815 8.7448620740265 -12.98968746794417 6.365850645371806 5.869259704768073 -12.01459862536752 6.365850645371814 4.419440650959615 -11.52107582106856 6.365850645371812 6.544932126263301 -31.90456185823363 3.165121083362622 8.092661106165284 -31.58975942400409 3.16512108336262 11.20460834914855 -30.90680113202703 3.165121083362622 14.84204730915133 -29.92134085942321 3.16512108336262 17.46752301247033 -29.01529022226459 3.165121083362621 18.82208165041136 -28.47886620924685 3.165121083362623 20.11351165996408 -27.88441381884321 3.165121083362622 21.31676039519302 -27.23458650057071 3.165121083362622 22.62017081513568 -26.36653815727195 3.16512108336262 23.91800584351515 -25.21903778729683 3.165121083362623 25.10334114378393 -23.59819383472133 3.165121083362621 25.99755520672941 -21.42290113737523 3.165121083362623 26.04664014523435 -18.97651604679795 3.165121083362622 25.90717939549378 -18.34239384704965 3.16512108336262 25.95225389747909 -16.86194730645456 3.165121083362621 24.42328245164322 -13.47609477801896 3.165121083362624 22.44190226756694 -12.08643987697811 3.165121083362621 21.15681886734338 -11.41706823917362 3.165121083362621 20.14076872489779 -11.04278419215928 3.165121083362622 18.74286602646018 -10.55189036258042 3.165121083362622 16.98292839335406 -9.966500148370677 3.165121083362622 14.10137459967804 -9.005034449774998 3.165121083362624 10.49792794100398 -7.796013189423029 3.16512108336262 7.631377254819007 -6.82394939570154 3.165121083362622 6.185957791823462 -6.331931719851966 3.165121083362622 6.552227369179164 -31.94043013590321 -3.133242188268291 8.100332849282111 -31.62555171736219 -3.133242188268288 11.21319272387025 -30.94239290695746 -3.13324218826829 14.85241063889563 -29.95647839531647 -3.133242188268289 17.48019463853902 -29.04964193510785 -3.133242188268291 18.83635187289273 -28.51259236247425 -3.13324218826829 20.12981200525016 -27.91721348704998 -3.133242188268291 21.33553389634529 -27.26606863117134 -3.133242188268291 22.64248344990492 -26.39569772562369 -3.13324218826829 23.94499959786068 -25.24416900103612 -3.13324218826829 25.13556135999972 -23.61629101813174 -3.13324218826829 26.034082285348 -21.43057284514151 -3.133242188268291 26.08331002017502 -18.97274833621811 -3.133242188268291 25.94340849307107 -18.33986751930276 -3.133242188268289 25.98935496752646 -16.85536072802017 -3.133242188268291 24.45241101397662 -13.45159924472399 -3.133242188268291 22.46112785629988 -12.0551487092541 -3.133242188268291 21.17111771306039 -11.38327500967671 -3.133242188268289 20.1531054714247 -11.00833541939656 -3.133242188268291 18.75450606023211 -10.51718150936773 -3.13324218826829 16.99450334868581 -9.931777984718943 -3.133242188268292 14.11297699946873 -8.970318642661926 -3.133242188268293 10.50963383038752 -7.761333045485572 -3.133242188268287 7.6431435857426 -6.789289451168993 -3.133242188268291 6.197753500492837 -6.297281825636106 -3.133242188268291 5.448753990631914 -26.51501935804593 -6.365850645371808 6.939910311732351 -26.21163427370404 -6.365850645371802 9.914726163383383 -25.55880574145748 -6.365850645371808 13.28486057677368 -24.64159911120771 -6.365850645371802 15.56349327698314 -23.85362569996547 -6.365850645371808 16.67784792781769 -23.411197840518 -6.365850645371807 17.66423309419971 -22.95595844607593 -6.365850645371808 18.49586714602469 -22.5041034137691 -6.365850645371808 19.26748980581282 -21.98504166149361 -6.365850645371806 19.86194305664204 -21.44283905879877 -6.365850645371808 20.26195382488489 -20.8789236198905 -6.365850645371807 20.50902173333118 -20.27015565468437 -6.365850645371807 20.53665019562085 -19.54264962269536 -6.365850645371808 20.46342034648161 -18.72199810032736 -6.365850645371802 20.37747287049962 -17.85164200910751 -6.365850645371811 20.04644489865411 -17.15677660428756 -6.365850645371807 19.55307865239526 -16.78822901451538 -6.365850645371808 19.00828423723232 -16.49481544158947 -6.365850645371804 18.2870577568549 -16.21903287056789 -6.365850645371807 16.99384263326964 -15.76721854883496 -6.365850645371808 15.2436836414032 -15.18382835195504 -6.365850645371807 12.35800606238126 -14.2214075242726 -6.365850645371811 8.739009129334717 -13.0070275399129 -6.3658506453718 5.863376539306287 -12.0319285976338 -6.365850645371809 4.413542796624924 -11.53840076817649 -6.365850645371808 4.356223476458425 -21.14341099669305 -3.16512108336262 5.790995388857798 -20.85140527008311 -3.165121083362618 8.629136164979027 -20.22860623835317 -3.16512108336262 12.05501700806195 -22.22563719026126 -2.345143718310979 14.38994662073503 -22.39134069324373 -2.173937593566638 15.8313062871318 -22.09643349855259 -2.138764637436656 16.85049178749752 -21.69904226161334 -2.131734126709232 17.62231712318653 -21.3046452436854 -2.130534434118307 18.2301643180315 -20.92168943299444 -2.130336185560891 18.66494284148709 -20.5667872180684 -2.130336185560891 18.934677580388 -20.22975730002421 -2.130336185560891 19.0718634375708 -19.8676933673787 -2.130336185560891 19.09508532774156 -19.43053763712961 -2.130336185560891 19.06740828562969 -18.9349682618302 -2.13033618556089 19.01813709518899 -18.4521522773468 -2.130336185560892 18.86691482145609 -18.09234547072512 -2.130336185560891 18.58422755803343 -17.88140404425846 -2.130534434118307 18.12657934820513 -17.69503019747387 -2.131734126709231 17.34622327950738 -17.46883087481896 -2.138764637436656 16.00381993170195 -17.2508559072494 -2.173937593566639 13.91461066246326 -17.48495643935594 -2.34514371831098 10.62043872497989 -19.42042269521366 -3.165121083362622 6.985943262357257 -18.20070181843402 -3.165121083362617 4.101258989255399 -17.22257782729976 -3.16512108336262 2.647025655761119 -16.72754486939306 -3.16512108336262 4.348928233542598 -21.10754271902344 3.13324218826829 5.783323645741007 -20.81561297672496 3.133242188268288 8.620551790257359 -20.19301446342274 3.13324218826829 12.05464630530952 -22.22276951190605 2.330029551600019 14.39156247147932 -22.39517433720579 2.163975056302921 15.83354835144833 -22.10154845012024 2.130118060962435 16.85313851838361 -21.70427869024211 2.123342581395765 17.62539715587625 -21.3096912106959 2.122175532793416 18.23382161025673 -20.92633496926805 2.121979324485286 18.66933062627186 -20.57073219600362 2.121979324485287 18.93984749014791 -20.23256675449064 2.121979324485286 19.07764013186653 -19.86894836611156 2.121979324485287 19.10098586093496 -19.43029231143374 2.121979324485287 19.07326642422995 -18.93438837705636 2.121979324485286 19.02386063935434 -18.45067871684275 2.121979324485287 18.87155225778202 -18.08868300324772 2.121979324485288 18.58749765363009 -17.87654013060773 2.122175532793416 18.12900246248176 -17.68970347916105 2.123342581395765 17.34817189531539 -17.46360243639077 2.130118060962434 16.00516710381799 -17.24693326358207 2.163975056302923 13.91370393379888 -17.48767197183128 2.330029551600021 10.60883632518916 -19.45513850232674 3.133242188268292 6.974237372973668 -18.23538196237149 3.133242188268287 4.089492658331778 -17.25723777183232 3.13324218826829 2.635229947091702 -16.76219476360893 3.13324218826829 5.45240161208984 -26.53295349688072 6.365850645371812 6.943746183290763 -26.22953042038311 6.365850645371806 9.919018350744217 -25.57660162892268 6.365850645371812 13.29004224164584 -24.65916787915436 6.365850645371809 15.56982909001747 -23.87080155638711 6.365850645371809 16.68498303905838 -23.42806091713169 6.365850645371812 17.67238326684275 -22.97235828017932 6.365850645371815 18.50525389660083 -22.51984447906943 6.365850645371811 19.27864612319744 -21.99962144566948 6.365850645371809 19.8754399338148 -21.45540466566841 6.365850645371814 20.27806393299279 -20.88797221159571 6.365850645371809 20.52728527264048 -20.27399150856752 6.365850645371812 20.55498513309119 -19.54076576740544 6.365850645371812 20.48153489527025 -18.72073493645393 6.365850645371808 20.39602340552332 -17.84834871989033 6.365850645371813 20.06100917982081 -17.14452883764008 6.365850645371815 19.56269144676174 -16.77258343065338 6.365850645371811 19.01543366009083 -16.47791882684101 6.365850645371813 18.29322613011837 -16.20180848418653 6.365850645371808 16.99966265015561 -15.74986412222862 6.365850645371813 15.24947111906908 -15.16646727012917 6.365850645371814 12.36380726227661 -14.20404962071607 6.365850645371815 8.7448620740265 -12.98968746794417 6.365850645371806 5.869259704768073 -12.01459862536752 6.365850645371814 4.419440650959615 -11.52107582106856 6.365850645371812 6.544932126263301 -31.90456185823363 3.165121083362622 8.092661106165284 -31.58975942400409 3.16512108336262 11.20460834914855 -30.90680113202703 3.165121083362622 14.84204730915133 -29.92134085942321 3.16512108336262 17.46752301247033 -29.01529022226459 3.165121083362621 18.82208165041136 -28.47886620924685 3.165121083362623 20.11351165996408 -27.88441381884321 3.165121083362622 21.31676039519302 -27.23458650057071 3.165121083362622 22.62017081513568 -26.36653815727195 3.16512108336262 23.91800584351515 -25.21903778729683 3.165121083362623 25.10334114378393 -23.59819383472133 3.165121083362621 25.99755520672941 -21.42290113737523 3.165121083362623 26.04664014523435 -18.97651604679795 3.165121083362622 25.90717939549378 -18.34239384704965 3.16512108336262 25.95225389747909 -16.86194730645456 3.165121083362621 24.42328245164322 -13.47609477801896 3.165121083362624 22.44190226756694 -12.08643987697811 3.165121083362621 21.15681886734338 -11.41706823917362 3.165121083362621 20.14076872489779 -11.04278419215928 3.165121083362622 18.74286602646018 -10.55189036258042 3.165121083362622 16.98292839335406 -9.966500148370677 3.165121083362622 14.10137459967804 -9.005034449774998 3.165121083362624 10.49792794100398 -7.796013189423029 3.16512108336262 7.631377254819007 -6.82394939570154 3.165121083362622 6.185957791823462 -6.331931719851966 3.165121083362622</coefs>
 </Geometry>
 <Geometry type="TensorBSpline2">
  <Basis type="TensorBSplineBasis2">
   <Basis type="BSplineBasis" index="0">
    <KnotVector degree="3">0 0 0 0 4.570609835176398 9.14506643581444 10.46788633955679 11.79109896711383 12.7555146347201 13.7206266801095 14.63194564671659 15.54813305244663 16.12521737949137 16.70481263559845 17.50476270818472 18.29512533029413 19.18363558575445 20.09961664790639 20.56315312673546 21.02366494080325 21.94846532611753 22.87152729068178 25.15958133910473 27.44759124303697 32.02021068748245 36.59282940448932 36.59282940448932 36.59282940448932 36.59282940448932</KnotVector>
   </Basis>
   <Basis type="BSplineBasis" index="1">
    <KnotVector degree="3">-3 -2 -1 0 1 2 3 4 5 6 7 8 9</KnotVector>
   </Basis>
  </Basis>
  <coefs geoDim="3"> -20.03471298272932 -21.10754271902344 3.13324218826829 -18.60031757053091 -20.81561297672496 3.133242188268288 -15.76308942601456 -20.19301446342274 3.13324218826829 -12.66114903674803 -19.34428859504558 3.133242188268289 -10.73051348781031 -18.67478532124473 3.13324218826829 -9.857162122288571 -18.32666639517545 3.133242188268289 -9.176836860479622 -18.01110323920528 3.133242188268291 -8.718054069991677 -17.75787926166718 3.13324218826829 -8.479988737166568 -17.58896538153939 3.133242188268289 -8.591257823675754 -17.65407472343106 3.133242188268291 -8.979184818393955 -18.15060481335447 3.133242188268289 -9.381416495648256 -19.11357431811037 3.13324218826829 -9.375315907734899 -20.11066705388268 3.133242188268291 -9.382094467591124 -19.10286551747852 3.133242188268288 -9.599499907775428 -18.84463000097766 3.133242188268291 -8.728598151773621 -20.84970619720364 3.133242188268291 -7.728998973414798 -21.50566373591465 3.13324218826829 -7.531041032009165 -21.58945925875375 3.13324218826829 -7.956462800723357 -21.41250593535786 3.133242188268289 -9.144641993078777 -20.99990116169584 3.13324218826829 -10.88498980448545 -20.41851763736526 3.133242188268291 -13.77480489108276 -19.45513850232674 3.133242188268292 -17.40940384329825 -18.23538196237149 3.133242188268287 -20.29414855794014 -17.25723777183232 3.13324218826829 -21.74841126918022 -16.76219476360893 3.13324218826829 -18.93123960418208 -26.53295349688072 6.365850645371812 -17.43989503298116 -26.22953042038311 6.365850645371806 -14.4646228655277 -25.57660162892268 6.365850645371812 -11.09359897462608 -24.65916787915436 6.365850645371809 -8.813812126254444 -23.87080155638711 6.365850645371809 -7.698658177213542 -23.42806091713169 6.365850645371812 -6.711257949429172 -22.97235828017932 6.365850645371815 -5.878387319671091 -22.51984447906943 6.365850645371811 -5.104995093074478 -21.99962144566948 6.365850645371809 -4.508201282457119 -21.45540466566841 6.365850645371814 -4.105577283279128 -20.88797221159571 6.365850645371809 -3.856355943631441 -20.27399150856752 6.365850645371812 -3.828656083180732 -19.54076576740544 6.365850645371812 -3.902106321001669 -18.72073493645393 6.365850645371808 -3.987617810748601 -17.84834871989033 6.365850645371813 -4.322632036451109 -17.14452883764008 6.365850645371815 -4.820949769510183 -16.77258343065338 6.365850645371811 -5.368207556181091 -16.47791882684101 6.365850645371813 -6.090415086153553 -16.20180848418653 6.365850645371808 -7.383978566116307 -15.74986412222862 6.365850645371813 -9.134170097202837 -15.16646727012917 6.365850645371814 -12.01983395399531 -14.20404962071607 6.365850645371815 -15.63877914224542 -12.98968746794417 6.365850645371806 -18.51438151150385 -12.01459862536752 6.365850645371814 -19.9642005653123 -11.52107582106856 6.365850645371812 -17.83870909000862 -31.90456185823363 3.165121083362622 -16.29098011010663 -31.58975942400409 3.16512108336262 -13.17903286712336 -30.90680113202703 3.165121083362622 -9.541593907120591 -29.92134085942321 3.16512108336262 -6.916118203801589 -29.01529022226459 3.165121083362621 -5.561559565860565 -28.47886620924685 3.165121083362623 -4.270129556307834 -27.88441381884321 3.165121083362622 -3.0668808210789 -27.23458650057071 3.165121083362622 -1.763470401136241 -26.36653815727195 3.16512108336262 -0.4656353727567664 -25.21903778729683 3.165121083362623 0.719699927512006 -23.59819383472133 3.165121083362621 1.613913990457486 -21.42290113737523 3.165121083362623 1.662998928962435 -18.97651604679795 3.165121083362622 1.523538179221861 -18.34239384704965 3.16512108336262 1.568612681207168 -16.86194730645456 3.165121083362621 0.03964123537130315 -13.47609477801896 3.165121083362624 -1.94173894870498 -12.08643987697811 3.165121083362621 -3.226822348928539 -11.41706823917362 3.165121083362621 -4.242872491374125 -11.04278419215928 3.165121083362622 -5.640775189811739 -10.55189036258042 3.165121083362622 -7.40071282291786 -9.966500148370677 3.165121083362622 -10.28226661659388 -9.005034449774998 3.165121083362624 -13.88571327526794 -7.796013189423029 3.16512108336262 -16.75226396145291 -6.82394939570154 3.165121083362622 -18.19768342444846 -6.331931719851966 3.165121083362622 -17.83141384709275 -31.94043013590321 -3.133242188268291 -16.28330836698981 -31.62555171736219 -3.133242188268288 -13.17044849240166 -30.94239290695746 -3.13324218826829 -9.531230577376288 -29.95647839531647 -3.133242188268289 -6.9034465777329 -29.04964193510785 -3.133242188268291 -5.547289343379182 -28.51259236247425 -3.13324218826829 -4.253829211021758 -27.91721348704998 -3.133242188268291 -3.048107319926631 -27.26606863117134 -3.133242188268291 -1.741157766367001 -26.39569772562369 -3.13324218826829 -0.4386416184112357 -25.24416900103612 -3.13324218826829 0.7519201437278035 -23.61629101813174 -3.13324218826829 1.650441069076083 -21.43057284514151 -3.133242188268291 1.699668803903105 -18.97274833621811 -3.133242188268291 1.55976727679915 -18.33986751930276 -3.133242188268289 1.605713751254541 -16.85536072802017 -3.133242188268291 0.06876979770470348 -13.45159924472399 -3.133242188268291 -1.922513359972037 -12.0551487092541 -3.133242188268291 -3.212523503211527 -11.38327500967671 -3.133242188268289 -4.230535744847215 -11.00833541939656 -3.133242188268291 -5.629135156039808 -10.51718150936773 -3.13324218826829 -7.389137867586111 -9.931777984718943 -3.133242188268292 -10.27066421680319 -8.970318642661926 -3.133242188268293 -13.8740073858844 -7.761333045485572 -3.133242188268287 -16.74049763052932 -6.789289451168993 -3.133242188268291 -18.18588771577908 -6.297281825636106 -3.133242188268291 -18.93488722564 -26.51501935804593 -6.365850645371808 -17.44373090453957 -26.21163427370404 -6.365850645371802 -14.46891505288854 -25.55880574145748 -6.365850645371808 -11.09878063949824 -24.64159911120771 -6.365850645371802 -8.820147939288779 -23.85362569996547 -6.365850645371808 -7.705793288454226 -23.411197840518 -6.365850645371807 -6.71940812207221 -22.95595844607593 -6.365850645371808 -5.887774070247223 -22.5041034137691 -6.365850645371808 -5.116151410459096 -21.98504166149361 -6.365850645371806 -4.521698159629882 -21.44283905879877 -6.365850645371808 -4.121687391387026 -20.8789236198905 -6.365850645371807 -3.87461948294074 -20.27015565468437 -6.365850645371807 -3.846991020651069 -19.54264962269536 -6.365850645371808 -3.920220869790314 -18.72199810032736 -6.365850645371802 -4.006168345772293 -17.85164200910751 -6.365850645371811 -4.337196317617808 -17.15677660428756 -6.365850645371807 -4.830562563876658 -16.78822901451538 -6.365850645371808 -5.375356979039601 -16.49481544158947 -6.365850645371804 -6.096583459417015 -16.21903287056789 -6.365850645371807 -7.389798583002277 -15.76721854883496 -6.365850645371808 -9.139957574868722 -15.18382835195504 -6.365850645371807 -12.02563515389065 -14.2214075242726 -6.365850645371811 -15.6446320869372 -13.0070275399129 -6.3658506453718 -18.52026467696563 -12.0319285976338 -6.365850645371809 -19.97009841964699 -11.53840076817649 -6.365850645371808 -20.02741773981349 -21.14341099669305 -3.16512108336262 -18.59264582741412 -20.85140527008311 -3.165121083362618 -15.75450505129289 -20.22860623835317 -3.16512108336262 -12.65078570700375 -19.37942613093889 -3.165121083362618 -10.71784186174166 -18.70913703408803 -3.16512108336262 -9.842891899807217 -18.36039254840287 -3.16512108336262 -9.160536515193566 -18.0439029074121 -3.165121083362619 -8.699280568839429 -17.78936139226787 -3.165121083362621 -8.457676102397347 -17.61812494989116 -3.165121083362619 -8.564264069330227 -17.6792059371704 -3.16512108336262 -8.946964602178154 -18.16870199676494 -3.16512108336262 -9.344889417029641 -19.1212460258767 -3.16512108336262 -9.338646032794196 -20.10689934330288 -3.16512108336262 -9.345865370013808 -19.10033918973168 -3.165121083362618 -9.562398837728022 -18.83804342254331 -3.16512108336262 -8.699469589440183 -20.82521066390868 -3.16512108336262 -7.709773384681808 -21.47437256819064 -3.16512108336262 -7.51674218629211 -21.55566602925683 -3.165121083362619 -7.944126054196402 -21.37805716259512 -3.16512108336262 -9.133001959306796 -20.96519230848315 -3.165121083362619 -10.87341484915365 -20.3837954737135 -3.16512108336262 -13.76320249129203 -19.42042269521366 -3.165121083362622 -17.39769795391466 -18.20070181843402 -3.165121083362617 -20.28238222701652 -17.22257782729976 -3.16512108336262 -21.7366155605108 -16.72754486939306 -3.16512108336262 -20.03471298272932 -21.10754271902344 3.13324218826829 -18.60031757053091 -20.81561297672496 3.133242188268288 -15.76308942601456 -20.19301446342274 3.13324218826829 -12.66114903674803 -19.34428859504558 3.133242188268289 -10.73051348781031 -18.67478532124473 3.13324218826829 -9.857162122288571 -18.32666639517545 3.133242188268289 -9.176836860479622 -18.01110323920528 3.133242188268291 -8.718054069991677 -17.75787926166718 3.13324218826829 -8.479988737166568 -17.58896538153939 3.133242188268289 -8.591257823675754 -17.65407472343106 3.133242188268291 -8.979184818393955 -18.15060481335447 3.133242188268289 -9.381416495648256 -19.11357431811037 3.13324218826829 -9.375315907734899 -20.11066705388268 3.133242188268291 -9.382094467591124 -19.10286551747852 3.133242188268288 -9.599499907775428 -18.84463000097766 3.133242188268291 -8.728598151773621 -20.84970619720364 3.133242188268291 -7.728998973414798 -21.50566373591465 3.13324218826829 -7.531041032009165 -21.58945925875375 3.13324218826829 -7.956462800723357 -21.41250593535786 3.133242188268289 -9.144641993078777 -20.99990116169584 3.13324218826829 -10.88498980448545 -20.41851763736526 3.133242188268291 -13.77480489108276 -19.45513850232674 3.133242188268292 -17.40940384329825 -18.23538196237149 3.133242188268287 -20.29414855794014 -17.25723777183232 3.13324218826829 -21.74841126918022 -16.76219476360893 3.13324218826829 -18.93123960418208 -26.53295349688072 6.365850645371812 -17.43989503298116 -26.22953042038311 6.365850645371806 -14.4646228655277 -25.57660162892268 6.365850645371812 -11.09359897462608 -24.65916787915436 6.365850645371809 -8.813812126254444 -23.87080155638711 6.365850645371809 -7.698658177213542 -23.42806091713169 6.365850645371812 -6.711257949429172 -22.97235828017932 6.365850645371815 -5.878387319671091 -22.51984447906943 6.365850645371811 -5.104995093074478 -21.99962144566948 6.365850645371809 -4.508201282457119 -21.45540466566841 6.365850645371814 -4.105577283279128 -20.88797221159571 6.365850645371809 -3.856355943631441 -20.27399150856752 6.365850645371812 -3.828656083180732 -19.54076576740544 6.365850645371812 -3.902106321001669 -18.72073493645393 6.365850645371808 -3.987617810748601 -17.84834871989033 6.365850645371813 -4.322632036451109 -17.14452883764008 6.365850645371815 -4.820949769510183 -16.77258343065338 6.365850645371811 -5.368207556181091 -16.47791882684101 6.365850645371813 -6.090415086153553 -16.20180848418653 6.365850645371808 -7.383978566116307 -15.74986412222862 6.365850645371813 -9.134170097202837 -15.16646727012917 6.365850645371814 -12.01983395399531 -14.20404962071607 6.365850645371815 -15.63877914224542 -12.98968746794417 6.365850645371806 -18.51438151150385 -12.01459862536752 6.365850645371814 -19.9642005653123 -11.52107582106856 6.365850645371812 -17.83870909000862 -31.90456185823363 3.165121083362622 -16.29098011010663 -31.58975942400409 3.16512108336262 -13.17903286712336 -30.90680113202703 3.165121083362622 -9.541593907120591 -29.92134085942321 3.16512108336262 -6.916118203801589 -29.01529022226459 3.165121083362621 -5.561559565860565 -28.47886620924685 3.165121083362623 -4.270129556307834 -27.88441381884321 3.165121083362622 -3.0668808210789 -27.23458650057071 3.165121083362622 -1.763470401136241 -26.36653815727195 3.16512108336262 -0.4656353727567664 -25.21903778729683 3.165121083362623 0.719699927512006 -23.59819383472133 3.165121083362621 1.613913990457486 -21.42290113737523 3.165121083362623 1.662998928962435 -18.97651604679795 3.165121083362622 1.523538179221861 -18.34239384704965 3.16512108336262 1.568612681207168 -16.86194730645456 3.165121083362621 0.03964123537130315 -13.47609477801896 3.165121083362624 -1.94173894870498 -12.08643987697811 3.165121083362621 -3.226822348928539 -11.41706823917362 3.165121083362621 -4.242872491374125 -11.04278419215928 3.165121083362622 -5.640775189811739 -10.55189036258042 3.165121083362622 -7.40071282291786 -9.966500148370677 3.165121083362622 -10.28226661659388 -9.005034449774998 3.165121083362624 -13.88571327526794 -7.796013189423029 3.16512108336262 -16.75226396145291 -6.82394939570154 3.165121083362622 -18.19768342444846 -6.331931719851966 3.165121083362622</coefs>
 </Geometry>
</xml>

