 <?xml version="1.0" encoding="UTF-8"?>
<!--
This is a simple example of two squares, parametrized by linear 
B-splines meeting along one side
-->
<xml>
  <!-- Patch 0 -->
<Geometry type="TensorBSpline2" id="5">
    <Basis type="TensorBSplineBasis2">
        <Basis type="BSplineBasis" index="0">
            <KnotVector degree="3">0 0 0 0 0.5 0.5 1 1 1 1</KnotVector>
        </Basis>
        <Basis type="BSplineBasis" index="1">
            <KnotVector degree="3">0 0 0 0 0.5 0.5 1 1 1 1</KnotVector>
        </Basis>
    </Basis>
    <coefs geoDim="2">
    0 0.5 
    0.4166666667 1.083333333 
    0.846 1.666 
    1.679333333 2.832666667 
    2.083333333 3.416666667 
    2.5 4 
    1 0.1666666667 
    1.322 0.627 
    1.685 1.297 
    2.384133074 2.765481446 
    2.631614517 3.379958429 
    2.916666667 4 
    1.926 -0.309 
    2.179 0.149 
    2.638 1.263 
    2.971 2.34 
    3.25 3.28 
    3.333333333 4 
    3.592666667 -1.642333333 
    3.779921032 -0.7747409619 
    3.903 0.087
    4.137 2.103 
    4.154 3.016 
    4.166666667 4
    4.333333333 -2.5 
    4.470143002 -1.394209764 
    4.532 -0.354 
    4.604 1.773 
    4.619 2.874 
    4.583333333 4
    5 -3.5 
    5 -2.25 
    5 -1 
    5 1.5 
    5 2.75
    5 4
    </coefs>
 </Geometry>

  <!-- Patch 1 -->
<Geometry type="TensorBSpline2" id="1">
    <Basis type="TensorBSplineBasis2">
        <Basis type="BSplineBasis" index="0">
            <KnotVector degree="3">0 0 0 0 0.5 0.5 1 1 1 1</KnotVector>
        </Basis>
        <Basis type="BSplineBasis" index="1">
            <KnotVector degree="3">0 0 0 0 0.5 0.5 1 1 1 1</KnotVector>
        </Basis>
    </Basis>
    <coefs geoDim="2">
    0 0.5 
    -0.5 0.6666666667 
    -1.02 0.811 
    -2.02 1.144333333 
    -2.5 1.333333333 
    -3 1.5 
    0.4166666667 1.083333333 
    -0.07448824786 1.306227564 
    -0.563 1.438 
    -1.480167963 1.629361526 
    -1.966776584 1.771412706 
    -2.5 1.916666667 
    0.846 1.666 
    0.3493072426 1.855898439
    -0.097 1.778 
    -1.082 2.168 
    -1.553 2.191 
    -2 2.333333333 
    1.679333333 2.832666667 
    1.16288045 2.850140752 
    0.799 3.009 
    -0.115 3.023 
    -0.525 3.127 
    -1 3.166666667 
    2.083333333 3.416666667 
    1.607195006 3.40993046
    1.252 3.461 
    0.333 3.527 
    -0.07 3.559 
    -0.5 3.583333333 
    2.5 4
    2.083333333 4 
    1.666666667 4 
    0.8333333333 4 
    0.4166666667 4 
    0 4
    </coefs>
 </Geometry>

    <!-- Patch 2 -->
<Geometry type="TensorBSpline2" id="2">
    <Basis type="TensorBSplineBasis2">
        <Basis type="BSplineBasis" index="0">
            <KnotVector degree="3">0 0 0 0 0.5 0.5 1 1 1 1</KnotVector>
        </Basis>
        <Basis type="BSplineBasis" index="1">
            <KnotVector degree="3">0 0 0 0 0.5 0.5 1 1 1 1</KnotVector>
        </Basis>
    </Basis>
    <coefs geoDim="2">
    0 0.5 
    -1 0.1666666667 
    -1.936 -0.312 
    -3.602666667 -1.645333333
    -4.333333333 -2.5 
    -5 -3.5 
    -0.5 0.6666666667 
    -1.399040763 0.292486522
    -2.163 -0.183 
    -3.797382482 -1.220869404 
    -4.406205118 -1.931915208 
    -5 -2.666666667 
    -1.02 0.811 
    -1.817956664 0.5104078099 
    -2.73 0.216 
    -3.921 -0.757 
    -4.559 -1.206 
    -5 -1.833333333 
    -2.02 1.144333333 
    -2.597815613 1.04307894 
    -3.171 0.698 
    -4.214 0.348 
    -4.633 0.043 
    -5 -0.1666666667
    -2.5 1.333333333 
    -2.945084883 1.285418744 
    -3.528 1.097 
    -4.26 0.908
    -4.691 0.778 
    -5 0.6666666667 
    -3 1.5 
    -3.333333333 1.5 
    -3.666666667 1.5 
    -4.333333333 1.5 
    -4.666666667 1.5 
    -5 1.5
    </coefs>
 </Geometry>

  <!-- Patch 3 -->
  <Geometry type="TensorBSpline2" id="3">
    <Basis type="TensorBSplineBasis2">
        <Basis type="BSplineBasis" index="0">
            <KnotVector degree="3">0 0 0 0 0.5 0.5 1 1 1 1</KnotVector>
        </Basis>
        <Basis type="BSplineBasis" index="1">
            <KnotVector degree="3">0 0 0 0 0.5 0.5 1 1 1 1</KnotVector>
        </Basis>
    </Basis>
    <coefs geoDim="2">
    0 0.5 
    0 0.1666666667 
    -0.00009804404997 -0.1839879739
    -0.00009804404997 -0.8506546406 
    0 -1.166666667 
    0 -1.5 
    -1 0.1666666667 
    -0.9563851633 -0.1239247936 
    -0.884 -0.412 
    -0.784 -0.957 
    -0.72 -1.222 
    -0.6666666667 -1.5 
    -1.936 -0.312 
    -1.858580681 -0.5562969462 
    -1.623 -0.762 
    -1.446 -1.21 
    -1.272 -1.446 
    -1.166666667 -1.666666667 
    -3.602666667 -1.645333333 
    -3.20990102 -1.86004771 
    -3.05 -1.869 
    -2.385 -2.141 
    -2.147 -2.208 
    -1.833333333 -2.333333333
    -4.333333333 -2.5 
    -3.903119097 -2.593331868 
    -3.585 -2.586 
    -2.758 -2.729 
    -2.403 -2.771 
    -2 -2.833333333 
    -5 -3.5 
    -4.5 -3.5 
    -4 -3.5 
    -3 -3.5 
    -2.5 -3.5 
    -2 -3.5
    </coefs>
  </Geometry>
  
    <!-- Patch 4 -->
<Geometry type="TensorBSpline2" id="4">
    <Basis type="TensorBSplineBasis2">
        <Basis type="BSplineBasis" index="0">
            <KnotVector degree="3">0 0 0 0 0.5 0.5 1 1 1 1</KnotVector>
        </Basis>
        <Basis type="BSplineBasis" index="1">
            <KnotVector degree="3">0 0 0 0 0.5 0.5 1 1 1 1</KnotVector>
        </Basis>
    </Basis>
    <coefs geoDim="2">
    0 0.5 
    1 0.1666666667 
    1.926 -0.309 
    3.592666667 -1.642333333 
    4.333333333 -2.5 
    5 -3.5 
    0 0.1666666667 
    0.9562544379 -0.1213925049 
    1.791740667 -0.5631997981 
    3.235713725 -1.893982928 
    3.871061208 -2.694861321 
    4.5 -3.5 
    -0.00009804404997 -0.1839879739 
    0.8837385492 -0.4119679305 
    1.665 -0.759 
    3.026 -1.844 
    3.596 -2.523 
    4 -3.5
    -0.00009804404997 -0.8506546406 
    0.7838692746 -0.9549839652 
    1.418 -1.213 
    2.397 -2.158 
    2.751 -2.772 
    3 -3.5 
    0 -1.166666667 
    0.72 -1.222444444 
    1.29 -1.444 
    2.137 -2.197 
    2.407 -2.741 
    2.5 -3.5 
    0 -1.5 
    0.6666666667 -1.5 
    1.166666667 -1.666666667 
    1.833333333 -2.333333333
    2 -2.833333333 
    2 -3.5
    </coefs>
 </Geometry>
  
  <!-- A multipatch section describes the configuration
       of the two patches above -->
  <MultiPatch parDim="2" id="0">
    <patches type="id_range">1 5</patches>
  </MultiPatch>

</xml>
