<?xml version="1.0" encoding="UTF-8"?>
<!--This file was created by G+Smo 0.8.5-->
<xml>
 <Geometry type="TensorBSpline2" id="0">
  <Basis type="TensorBSplineBasis2">
   <Basis type="BSplineBasis" index="0">
    <KnotVector degree="2">0 0 0 0.02631578947368421 0.05263157894736842 0.07894736842105263 0.1052631578947368 0.131578947368421 0.1578947368421053 0.1842105263157895 0.2105263157894737 0.2368421052631579 0.2631578947368421 0.2894736842105263 0.3157894736842105 0.3421052631578947 0.3684210526315789 0.3947368421052632 0.4210526315789473 0.4473684210526315 0.4736842105263158 0.5 0.5263157894736842 0.5526315789473684 0.5789473684210527 0.6052631578947368 0.6052631578947368 0.631578947368421 0.6578947368421052 0.6842105263157894 0.7105263157894737 0.7368421052631579 0.763157894736842 0.7894736842105263 0.8157894736842105 0.8421052631578947 0.8684210526315789 0.8947368421052631 0.9210526315789473 0.9473684210526315 0.9736842105263157 1 1 1 </KnotVector>
   </Basis>
   <Basis type="BSplineBasis" index="1">
    <KnotVector degree="2">0 0 0 0.07692307692307693 0.1538461538461539 0.2307692307692308 0.3076923076923077 0.3846153846153846 0.4615384615384616 0.5384615384615385 0.6153846153846154 0.6923076923076923 0.7692307692307693 0.8461538461538463 0.9230769230769231 1 1 1 </KnotVector>
   </Basis>
  </Basis>
  <coefs geoDim="2">-0.2338756033185635 0.1498756017487116 
-0.2307774331772131 0.1547101758507939 
-0.2241869587723681 0.1641148076944233 
-0.2172133857337382 0.1732391651063965 
-0.2098687387778967 0.1820675014638225 
-0.2021655211333609 0.1905847977057199 
-0.1941169129057336 0.1987764747508202 
-0.1857366566785122 0.2066285490886036 
-0.1770390735498984 0.2141276004989134 
-0.1680390216901543 0.2212608191369386 
-0.1587518781887293 0.2280160170891309 
-0.1491935096537517 0.2343816536415074 
-0.1393802465507536 0.2403468530138081 
-0.1293288546477176 0.2459014238259788 
-0.119056506549075 0.2510358761844615 
-0.1085807523910333 0.2557414379680821 
-0.09791948986600302 0.2600100697814367 
-0.08709093353827166 0.2638344787534325 
-0.07611358378234219 0.2672081309531281 
-0.06500619525340108 0.2701252625398108 
-0.0537877447606861 0.272580889640276 
-0.04247739877804989 0.2745708168700859 
-0.03109448086327889 0.2760916444652141 
-0.01965843857977901 0.2771407741130322 
-0.01392362438058222 0.2774285937563711 
-0.008188810181385418 0.27771641339971 
0.003294808692057897 0.2778175788517583 
0.01477279842283311 0.2774440976321041 
0.02622554905829406 0.2765966078222597 
0.03763349379233089 0.2752765573591665 
0.0489771423939623 0.2734862014811011 
0.06023711420832319 0.2712285990960145 
0.07139417223284869 0.2685076070244842 
0.08242925384067169 0.2653278746077073 
0.0933235080488443 0.2616948330324322 
0.1040583168388868 0.257614692415459 
0.1146153524802239 0.2530944163377334 
0.1249765494741998 0.2481417444731901 
0.1351242734927291 0.242765099018049 
0.1450410210104867 0.2369737631044463 
0.1498756017487116 0.2338756033185635 
-0.2433427034404578 0.1559424480013818 
-0.2408344833384156 0.1628579872578701 
-0.2336499342290383 0.1739582742570433 
-0.226214352167703 0.1848109186368719 
-0.2182345369609694 0.1952813127260601 
-0.2097991520365782 0.2054550016118422 
-0.2009164295948571 0.2152862579291503 
-0.1916388713941873 0.2247435482477553 
-0.1820191588141045 0.2337828734465429 
-0.1721183570657873 0.2423685587735789 
-0.1619972423717189 0.2504695490802526 
-0.15171329086701 0.2580638481299046 
-0.1413163294863924 0.2651371811275672 
-0.1308457990635311 0.2716825137821972 
-0.1203291094663156 0.2776978217918348 
-0.1097810600923987 0.2831834343983494 
-0.09920361636402414 0.2881375925700669 
-0.08858594394281807 0.2925511817560222 
-0.07790544149614873 0.296400197495713 
-0.06713214510932239 0.2996378040387547 
-0.05624099592574366 0.3021930996434806 
-0.04523133739500283 0.3040013636474513 
-0.03412570711338392 0.3050626801938516 
-0.02293829472625836 0.3054470657573672 
-0.01729968756811483 0.3053387945036889 
-0.01166115705698839 0.3052330988412942 
-0.0002778610497866275 0.3044758835685716 
0.01122526068352843 0.3032084022578625 
0.02285336418173904 0.30144155942615 
0.03460100109396614 0.2991777366971658 
0.04645114159540641 0.2964130407398167 
0.05837477285141591 0.2931418436376511 
0.07033148970244742 0.2893588726116325 
0.08227184990627871 0.2850622541110008 
0.09413974047948744 0.2802526070106839 
0.1058792751819982 0.2749389453351554 
0.1174326052844716 0.269119717617252 
0.1287742945405737 0.262824770542896 
0.1398474310964148 0.2559278131977262 
0.1508597483173349 0.2486875278288386 
0.1559424480013818 0.2433427034404578 
-0.2622769036842463 0.1680761405067222 
-0.2594884332746307 0.1756934004465769 
-0.2521847323869739 0.1904937980612423 
-0.2438007871105808 0.2043596471006308 
-0.234720345585206 0.2178472652863815 
-0.2250899404937829 0.2309697346648917 
-0.2150410210464688 0.2437384020587995 
-0.2046963040789317 0.2561337636882929 
-0.1941690349507031 0.2681263044207717 
-0.183556863926819 0.2796924926481389 
-0.1729344213485367 0.2908129035952383 
-0.1623489800411564 0.3014713475151611 
-0.1518196624827004 0.3116506279015461 
-0.1413395185209808 0.3213282580448222 
-0.1308785737881717 0.3304714231724241 
-0.1203863540201633 0.3390299807418206 
-0.1097941660470762 0.3469283360533783 
-0.09901796124196903 0.3540530323660914 
-0.08796392531078136 0.3602351605937744 
-0.07654497332570194 0.3652301730456575 
-0.06472219829024424 0.3687254434725422 
-0.05256822716864072 0.3704563363842914 
-0.04025340726201594 0.3704152602853772 
-0.02791855371701327 0.368867769416245 
-0.02176247776842544 0.3675039027924194 
-0.0156067984893743 0.3661416949466308 
-0.003297781273054128 0.3625070410974774 
0.009051871981073449 0.3581535568719714 
0.02148858002227203 0.3532103321612758 
0.03405009662976034 0.3477627575174839 
0.04676179834356239 0.341865896271375 
0.05963240620800597 0.3355525626642089 
0.07265080688784832 0.3288377581181378 
0.08578289395742456 0.3217213351933955 
0.09897188043819843 0.3141910875658316 
0.1121404604134238 0.306221573522738 
0.1251983008100437 0.29777809024945 
0.1380458698771157 0.288769313387428 
0.1505703643630705 0.2791437858866556 
0.1626319453967398 0.2682246173466805 
0.1680761405067222 0.2622769036842464 
-0.281211103928035 0.1802098330120626 
-0.2780490123791913 0.1889269523917509 
-0.2699628734310832 0.2058803764740175 
-0.2607198321458216 0.2226059491489285 
-0.2506180006387604 0.2388536473443358 
-0.240031592472734 0.2548447594952151 
-0.2291595388500419 0.2705283590980535 
-0.218204148965349 0.2859213772531397 
-0.2073093862683773 0.3009978259712714 
-0.1965730069194982 0.3157389018450653 
-0.1860360041408143 0.3301166899401867 
-0.1756884818172406 0.3440976893857419 
-0.1654774581968488 0.3576370777830641 
-0.1553158808249571 0.3706748598369974 
-0.1450894821202175 0.3831289056701808 
-0.1346637987638362 0.3948891113379339 
-0.1238910096426212 0.4058072899106436 
-0.1126164810494984 0.4156805479676586 
-0.1006891211539368 0.4242194609411664 
-0.0879906522547841 0.4310111810418539 
-0.07451055677575799 0.4355250140321658 
-0.06045636051964878 0.4373043172006486 
-0.04621494316418755 0.4363142845789422 
-0.03210629346024858 0.4329785442283794 
-0.02517855462772925 0.4304048157404967 
-0.01825207532470465 0.4278335204352569 
-0.004640048869312183 0.4213338817301786 
0.008802116853629622 0.4138130419925128 
0.02216777542067696 0.4055186216855095 
0.03554904747975508 0.3966348411242642 
0.04902698298640205 0.3872973404692361 
0.06266458406830011 0.3776028020339814 
0.07650061302389813 0.3676166813072441 
0.09054277376794333 0.357374431532348 
0.1047587931281883 0.3468798459363661 
0.1190741650206199 0.3361066978722402 
0.1333689516403834 0.3249789630084819 
0.1474878518694342 0.3134313463806278 
0.1612168046453872 0.3011612347220944 
0.1742319192599074 0.2882301378925428 
0.1802098330120626 0.281211103928035 
-0.3001453041718236 0.192343525517403 
-0.2964823650574839 0.2019314279989171 
-0.2873775428788555 0.2210844414425931 
-0.277144137641217 0.2401423820828885 
-0.2660965791038931 0.2590564442062167 
-0.2546851203791583 0.2778627380962758 
-0.2432052247547072 0.2965541788892191 
-0.2319213136229237 0.3151316807320164 
-0.2209955037915738 0.3335452748049438 
-0.2104964326853999 0.3517353141769397 
-0.2003998844022682 0.369618346950778 
-0.1906077712656758 0.3870979003487205 
-0.180965245721992 0.4040632071399641 
-0.1712765169099086 0.4203894736422069 
-0.1613233663567037 0.4359403932424447 
-0.1508824788214313 0.4505657373078658 
-0.1397361819463476 0.4640890020078341 
-0.1276778032200873 0.4762749094247303 
-0.1145217218883753 0.4867815309026255 
-0.100145744414052 0.4950994789344709 
-0.08460371672938205 0.50054982305819 
-0.06828462429642533 0.5025200023308636 
-0.05183175474039928 0.500924865487498 
-0.03575824422976741 0.4962718474981586 
-0.02800686822080684 0.4927442996234628 
-0.0202577932438154 0.4892197224081569 
-0.005312516800989497 0.4803259369941347 
0.00919060866737836 0.470002960758257 
0.02340641984049965 0.4585714469604945 
0.03749866684930344 0.4462990389318158 
0.05162511389091066 0.4334179313099236 
0.06591822117420847 0.4201272773113041 
0.08047439929355432 0.4065863246583933 
0.09534377038729071 0.3929154776461963 
0.1105202699654929 0.3791903664143661 
0.1259284937098981 0.3654211464300986 
0.1414163515085427 0.3515769403057628 
0.1567692690560044 0.3374891598767847 
0.1716843111052576 0.323078449952605 
0.1858492054520052 0.3080320178430153 
0.192343525517403 0.3001453041718236 
-0.3190795044156119 0.2044772180227434 
-0.3147872865570908 0.2148977799128806 
-0.3044939152581383 0.2360097241484867 
-0.2932039851422791 0.2574147301839754 
-0.2811546116575689 0.2788364109183716 
-0.2689653894349757 0.3005531538420297 
-0.2570155364877926 0.322419294272133 
-0.2456699396875097 0.3444430509048628 
-0.2350960686501848 0.3664566754464622 
-0.2253020660119535 0.3882861367931808 
-0.2161440719102039 0.4097233644308444 
-0.2073661989391538 0.4305660480174461 
-0.1986378887531604 0.4506268103823903 
-0.1896042666083582 0.4697504208735663 
-0.179928270552719 0.4878126198022597 
-0.1693095898736966 0.5047005543060514 
-0.1574835446032016 0.5202735737148803 
-0.1442139867599385 0.5343165511310961 
-0.1293026316715468 0.5464688144532482 
-0.1126501458150365 0.5561550153571341 
-0.09441763444321984 0.5625665995429296 
-0.07524137405023813 0.5649422608786835 
-0.05609234617578108 0.5631176491638855 
-0.03771498756547083 0.5576395931202053 
-0.02904774385740964 0.553445601760853 
-0.02038325127200232 0.5492520684571736 
-0.004070300813426077 0.5385770823035592 
0.01138416791205853 0.5260541940045125 
0.02620424055178764 0.5120107469139941 
0.0406470111971723 0.4967219668869116 
0.05498923590404878 0.4804663265635003 
0.06950244316786833 0.4635378642917725 
0.08440852537854919 0.4462377297288458 
0.099845882180972 0.4288382336815239 
0.1158475678420432 0.4115614741482711 
0.1323278190972123 0.3945507125816022 
0.1490763448993479 0.377825544185277 
0.1657624997894024 0.3612838895137078 
0.1820147711424856 0.3447173999048667 
0.1973920729834761 0.3277899509707736 
0.2044772180227434 0.3190795044156122 
-0.3380137046594006 0.2166109105280838 
-0.3330027079996575 0.227780339110106 
-0.3213577312250883 0.2507566709921801 
-0.3089526897309466 0.274412620998196 
-0.2957897525791522 0.2983430038862547 
-0.28281110412171 0.3231063201935233 
-0.2705714299279358 0.3484538023716858 
-0.2595923371338197 0.3742561818727078 
-0.2500189196238624 0.4000947183208611 
-0.2416898609076475 0.4255505521817342 
-0.2341846612461063 0.4502340558472711 
-0.2269336182261386 0.4738583720753703 
-0.2193494955579975 0.4962637481026042 
-0.2109251200324403 0.5173941427137595 
-0.2012597111205227 0.5372414228413072 
-0.1900382435248043 0.5557837233027441 
-0.1769964402293542 0.5729363988741558 
-0.161903854328267 0.5884999294815755 
-0.1445783154559145 0.6021031511940134 
-0.1249708490169933 0.6130998904561983 
-0.1033831546637885 0.6205582746123319 
-0.08074106637703247 0.623555863217658 
-0.05836950159463108 0.6218345372346095 
-0.03725887296489391 0.615954980798973 
-0.02751043533931799 0.6113451457835081 
-0.01776679619954832 0.6067379422194922 
0.000131702765002824 0.5948683171588502 
0.01662027487184221 0.5808188433001263 
0.03195764939973642 0.5648962408394536 
0.04645132632907433 0.5473259095388916 
0.06048069147633495 0.5282965891011933 
0.07449598544111352 0.5080739670687039 
0.08897534736189884 0.4870324246696677 
0.1043100471410635 0.4656456598261894 
0.1206976550740288 0.444405978503013 
0.138083817342565 0.4237217409150044 
0.1561522880558906 0.4038565210957922 
0.1743759705414356 0.3847259208724525 
0.1921539034949202 0.3661412316494055 
0.2088950353694621 0.3474509099103986 
0.2166109105280838 0.3380137046594008 
-0.3569479049031892 0.2287446030334241 
-0.3511136912011828 0.2406005972527941 
-0.3380089356166631 0.2653442833158854 
-0.3244340563576489 0.2911844727065508 
-0.3099488501421883 0.3175446122566702 
-0.29616358121243 0.3456673962027264 
-0.2840166045904741 0.3749336828415389 
-0.2742422183646644 0.4048598880932869 
-0.2667697344626511 0.4344872508516847 
-0.260937403414372 0.4630645687357044 
-0.2557381419711027 0.490122209961118 
-0.2501797133202897 0.515534118190166 
-0.2435021890127634 0.5393904593233921 
-0.2351970802185952 0.5618451032083024 
-0.2249276877540606 0.5830100226456995 
-0.2124372175259917 0.6029093631665923 
-0.1975085296147892 0.6214648068085361 
-0.1799505276956167 0.6384688351199667 
-0.159615972743052 0.6534997493260719 
-0.1365201789075836 0.6658631857801061 
-0.111122011073529 0.6745005158435814 
-0.08463800019427827 0.6783242717982128 
-0.05873060916520741 0.6769271804801541 
-0.03456917171432922 0.6708744309008583 
-0.02356864543948284 0.6659831905391053 
-0.0125705083306858 0.6610859119591913 
0.007287293206201868 0.6483247365341069 
0.02518132670530579 0.6331522584701994 
0.04133786587482694 0.6159187344485316 
0.05603332179617593 0.5967996593733293 
0.06961538779657778 0.5758936591913825 
0.08259074774856794 0.5532470212100964 
0.09568011243525358 0.5290499206897809 
0.1097443309318977 0.5037746791204449 
0.1254965051768274 0.4782080012524027 
0.143192055675577 0.4532585703821903 
0.1624757244776305 0.4297164748867336 
0.182456367705151 0.4077879091821458 
0.2020590349000755 0.3872947779597795 
0.2203311211852707 0.3670084458278695 
0.2287446030334241 0.3569479049031895 
-0.3758821051469777 0.2408782955387645 
-0.3691315747168908 0.2533511327958274 
-0.3545204371914227 0.2797708836581755 
-0.3397022285753147 0.3076764453476675 
-0.3235092770092728 0.3363878627510808 
-0.3089952456333563 0.3684102425140664 
-0.2978483834455009 0.4021953780221164 
-0.2908062105556267 0.4362915097399411 
-0.2869208819091339 0.4689820269595003 
-0.2843896787692911 0.499424943371923 
-0.2814801409327822 0.527604226676635 
-0.2770398419734295 0.5539035590602885 
-0.2704644647838086 0.5787306064561422 
-0.2614546747838133 0.6023365192165097 
-0.2498076531015127 0.6248131224583683 
-0.2353603898790635 0.6461397851423747 
-0.2179627164240938 0.6661922868912864 
-0.1974582679159563 0.6847134611804664 
-0.1737346065812521 0.7012699268921897 
-0.1468783831479768 0.7150873832170455 
-0.1174886140999559 0.7250524987745656 
-0.08707714754675283 0.7299037651911081 
-0.05759622497739603 0.7290267931433769 
-0.03035907376710455 0.7228832404908975 
-0.0180238087302617 0.7176897789004457 
-0.005695170111128694 0.7125083572787063 
0.01643032875803398 0.6988252997552916 
0.03618273739730775 0.6825580302604155 
0.05373867105385421 0.6640975681162522 
0.06925992132919008 0.6437548325906364 
0.08295426331217841 0.6215926065411395 
0.09513378163911114 0.5975402775954863 
0.106427947034905 0.5714053463088866 
0.1179955972890441 0.5431813654555588 
0.1314285603083822 0.5134697283585548 
0.14801969054096 0.4836774608625236 
0.1679145495396594 0.4556086695205547 
0.1898180437263862 0.4303711889166542 
0.2116796598224417 0.4081039001672044 
0.2317048307500842 0.3864471821319094 
0.2408782955387645 0.3758821051469777 
-0.3948163053907664 0.2530119880441049 
-0.387077978645183 0.2660564574299362 
-0.3710187594651311 0.2940210946685116 
-0.3547505543885119 0.3237882780021872 
-0.3362152062453972 0.3548650615649278 
-0.3214903067779303 0.3916973704963039 
-0.3132937419803178 0.4304279194183142 
-0.311201600470245 0.4677633440649785 
-0.3119775964131619 0.5016988805260978 
-0.31242035974102 0.532425649764886 
-0.3107175271714305 0.5609395098949389 
-0.3061968139033025 0.5880361925366555 
-0.298712425167543 0.6140997678011627 
-0.2881668566214849 0.6392150183493717 
-0.2744849157862264 0.6633452036064408 
-0.2575952569835375 0.6863660408842112 
-0.2373813577342978 0.7080808154796566 
-0.2137072097737669 0.728211534270253 
-0.1864699283331398 0.7463115087247775 
-0.1558015946382005 0.761690753144775 
-0.1225066236075849 0.7730987057759505 
-0.08834278059045519 0.7791955887454258 
-0.055538066295699 0.7790560480765577 
-0.02541388508787004 0.7729414329552899 
-0.01185257961841962 0.7673824055819083 
0.001735066945049268 0.7618678035585611 
0.02615352829882383 0.7470584928803198 
0.04807346685917902 0.7293279055900349 
0.06756069871354457 0.7094042015799847 
0.08467175978470975 0.6875785917564163 
0.09944319792070325 0.6641099995733335 
0.1119323556988633 0.6390076429398669 
0.1222891408964218 0.6120074518866581 
0.1312367286281698 0.5825151842931997 
0.1407117787373667 0.5501086905231179 
0.1537546462003891 0.5156264588651833 
0.1725526362603734 0.4819849561429972 
0.1961796308601354 0.4524400619083774 
0.220906025899928 0.4284371518411553 
0.2430533603518809 0.4057667988532822 
0.2530119880441049 0.3948163053907664 
-0.413750505634555 0.2651456805494453 
-0.4050550880275414 0.2787426134280289 
-0.3876871500935278 0.3080216783536433 
-0.3693473366743555 0.3394612747463239 
-0.3477226022419977 0.3731916991768633 
-0.3345352952149986 0.4160410498242058 
-0.3326818543414119 0.4588791364030902 
-0.3372580761983411 0.4967642544124772 
-0.3419581629831164 0.5298409886477276 
-0.3435382711783966 0.5603069036976785 
-0.3413846290486267 0.5897117972404777 
-0.3356718385562425 0.6184418261604475 
-0.3264738935602375 0.6464839829466833 
-0.3138109716497547 0.6736999043388731 
-0.297725063191118 0.6998955861808717 
-0.2781714409987972 0.7248462065179712 
-0.2550601940045082 0.7483130968532163 
-0.2282477063034277 0.7700146563585847 
-0.1976211876986116 0.7895807477278804 
-0.1633275227909761 0.8063974486969111 
-0.1262552323027688 0.819496498634206 
-0.08872937026238978 0.8271555366311025 
-0.05312338668444117 0.8280750210938201 
-0.02070460645378238 0.8221607222504491 
-0.006024254759087722 0.816277860813077 
0.008601223829499982 0.8103690941342224 
0.03523043377984733 0.7939325812164364 
0.05932736563172544 0.7744855496310733 
0.08103790186498414 0.7525568401072508 
0.1002892296487246 0.7287710806019849 
0.1169810233870954 0.7034178990627443 
0.1309889977499802 0.6767055101096681 
0.1421650660005576 0.6486859115278583 
0.1502570741843717 0.6189482531948733 
0.1560269122568357 0.5862129547081203 
0.1630031826947761 0.5491712913032514 
0.1771840075899758 0.5097152705074661 
0.2011827343510363 0.4741306607252744 
0.2295011674236809 0.4481504187041861 
0.2543750794841645 0.4250238498915839 
0.2651456805494453 0.413750505634555 
-0.4326847058783436 0.2772793730547857 
-0.4233280345219008 0.2915429198421969 
-0.4046761843778244 0.3215393268575261 
-0.3828671845145083 0.3545782755579722 
-0.3579913380068006 0.3921123826923644 
-0.3505435644207178 0.4409112754878738 
-0.3586151343719105 0.4844070698719355 
-0.3685963927217764 0.5194276731717589 
-0.3743559510922705 0.5516151778672005 
-0.374875134370325 0.583436793011293 
-0.3712616699079522 0.6152753566298249 
-0.3637042774954922 0.6467143882225177 
-0.3523210333140569 0.6775046665840583 
-0.3372921479554872 0.7073146564753021 
-0.3186624975560891 0.735848861933075 
-0.2964484375326978 0.7628357678094219 
-0.2705764537047758 0.7880123548578655 
-0.2409194509490848 0.8111254697839941 
-0.2073369385352083 0.8318847577681063 
-0.1699202917626294 0.8499191777087074 
-0.129562373590599 0.8644767131824179 
-0.08860112068277616 0.8745012006588941 
-0.05069746135480983 0.8773044251046794 
-0.01686614665228513 0.8720258300835492 
-0.001481379093299527 0.8653085880345835 
0.01416651369008232 0.8587627486755366 
0.04254155308652494 0.8408800356079733 
0.06880053663102983 0.8189873464491813 
0.09283288314450389 0.7947264400501922 
0.1144683062308618 0.7684719610539911 
0.1335467369752935 0.7406546271615834 
0.1498174846512599 0.7115066749736075 
0.1630436927872499 0.6812662030686808 
0.1728162770617461 0.650190031956898 
0.1779742146474834 0.6178535416537208 
0.1794282615288843 0.5820285440298758 
0.1844699173233757 0.5390935681312689 
0.2047188483732307 0.4962209597598839 
0.2369241566766544 0.4668619985005505 
0.2659104669033406 0.4440714619902947 
0.2772793730547856 0.4326847058783436 
-0.4516189061221322 0.2894130655601261 
-0.4419435357998972 0.3047777803227069 
-0.4219848677306366 0.3351208151148627 
-0.3947595080472447 0.3684108201926283 
-0.368501740040808 0.4122153138737653 
-0.3731352077001986 0.4630237496221734 
-0.3905640978716947 0.5012241394653933 
-0.4014168623141905 0.5339901568093373 
-0.4054296800490225 0.5687617485224696 
-0.4043449308305638 0.6042643992814423 
-0.3989347329084694 0.6397460069372322 
-0.389170476042693 0.6747202511085555 
-0.37547034643338 0.7087334416245935 
-0.3579475439177458 0.7414011549476072 
-0.3367711127594264 0.7723996148216283 
-0.3120016926243891 0.8014286883534666 
-0.2836580596956675 0.828224328713145 
-0.2516698015520583 0.8525429486521352 
-0.2159236660090212 0.8741729134439327 
-0.1764282353523393 0.8929237299012105 
-0.1338248477817522 0.9085521389516719 
-0.09019838901924772 0.9203404149783253 
-0.04857782715935378 0.9269493600007142 
-0.01334507846412735 0.9240014294423192 
0.002064709925580869 0.9160302259651304 
0.01731565380242203 0.9093590992517797 
0.04757234100268531 0.8882741305033678 
0.07601379844283555 0.8636557193386636 
0.1024219285858072 0.8366351931192914 
0.1265042810939058 0.8077085353492702 
0.1480487744995087 0.7771012775353867 
0.1668363772515959 0.7450303750835555 
0.1825013829210302 0.711713134146845 
0.1947739149781308 0.6773751952088055 
0.2029163507685778 0.6428316382563467 
0.2038149278115041 0.608133859782598 
0.1994292090660684 0.5681322198809121 
0.208007509352878 0.5200298782097569 
0.2431399080784886 0.483536456040765 
0.2774722499545029 0.4635362582140214 
0.2894130655601261 0.4516189061221322 
-0.4705531063659206 0.3015467580654664 
-0.4606092823506831 0.3177088140880297 
-0.4372591481825886 0.3511303501163625 
-0.4060135118714489 0.3818163927663764 
-0.3825473116225344 0.4289055340444386 
-0.403397506872608 0.4750054252619158 
-0.4225575053376686 0.5062480282119133 
-0.4308366188595572 0.5443533337530847 
-0.4338228399326486 0.5850775936447511 
-0.4312372099912097 0.6250592277408439 
-0.4236865529652541 0.6650498334619044 
-0.4116932654269025 0.7038986432305991 
-0.3954561151294544 0.7413694279686891 
-0.3753402493243136 0.7770376225599583 
-0.3515395947137686 0.8105744244216919 
-0.3242932881489333 0.8416859467475736 
-0.2937634187511394 0.8700886260599261 
-0.2600830628679286 0.8955441590658128 
-0.2233324755257398 0.9178378264345559 
-0.1836302988870273 0.9368703249115883 
-0.1413526116406849 0.9526013464865836 
-0.09762308095754678 0.9651157229580669 
-0.05427129445996558 0.9734699073962387 
-0.01397948054845281 0.9786879821441966 
0.0008117644392348447 0.9737702626875308 
0.01708650982264741 0.9615614232340661 
0.04960458745663675 0.9367113187760133 
0.08058192157065455 0.90875251845393 
0.1094696106694254 0.8789669917018027 
0.1360530314270809 0.8472492948809158 
0.1601252110880901 0.8137902654830008 
0.1814014963896977 0.7786509468990186 
0.1996395478287707 0.7419202004058455 
0.21426720820339 0.7039058412450735 
0.2251645460013067 0.6644655253973213 
0.2304784230917127 0.6243066366325577 
0.2253495222293909 0.5902082660496697 
0.2164534398104382 0.5415842569860494 
0.2477953187785828 0.4996674327383222 
0.2887122771141256 0.4826654548993452 
0.3015467580654664 0.4705531063659206 
-0.480020206487815 0.3076136043181367 
-0.467741991633106 0.3251392627218581 
-0.443026372084905 0.3611257992686552 
-0.4125395098560147 0.3898968814945436 
-0.3934107960515933 0.4326574157662427 
-0.4164788553282275 0.4700777015314581 
-0.4360297526861819 0.5080340648461896 
-0.4440918402393833 0.550882231411951 
-0.4468416734730813 0.5935057263882285 
-0.4431556778987453 0.6365677247566861 
-0.4346503456128441 0.6786337043701856 
-0.4213027216213255 0.7195786312715886 
-0.4037245833453047 0.7588047797065669 
-0.3821574989437372 0.7960283309705216 
-0.3569782927714444 0.8308856872911585 
-0.3284867362804281 0.8631018504595371 
-0.2970150646246969 0.8924066199687009 
-0.2628854627038504 0.9185695148794506 
-0.2264333090978847 0.9413830353103293 
-0.1879985983723529 0.960669904478456 
-0.1479300084512302 0.9762805088916339 
-0.1065830065564927 0.9880945469350801 
-0.06431771217544133 0.996021311249744 
-0.0215016682701733 0.9999997690318808 
6.167905692361981e-17 1 
0.01742515076107417 0.9874202157252512 
0.05076797945819725 0.960295943423742 
0.082420762781111 0.9312128827774434 
0.1121723669543636 0.9001893025082547 
0.1397951205868755 0.867246471752896 
0.1650085647153448 0.8324369903943561 
0.1875309708068749 0.7957946309188975 
0.2069298404729074 0.7574653654504614 
0.2228976003731496 0.7174511602392416 
0.2345960148731399 0.6762336945771883 
0.2414092119649325 0.6333954472304852 
0.2389892501831673 0.5908003656785924 
0.2258117123714905 0.548435209485303 
0.2504450901911786 0.5098428081066575 
0.2900879459144153 0.4922984213425241 
0.3076136043181367 0.480020206487815 
</coefs>
 </Geometry>
 <MultiPatch parDim="2" id="1">
  <patches type="id_range">0 0</patches>
  <boundary>0 4
0 3
0 2
0 1
</boundary>
 </MultiPatch>
</xml>

